{"name":"Tiago Ferreira","tagline":"","body":"### Contact details\r\n**E-mail:** TiagoJDFerreira@gmail.com \r\n\r\n <br />\r\n### Work Experience\r\n\r\n-----------------------------------\r\n\r\n**01/08/2014–31/08/2014\tResearch assistant**\r\n\r\n*Karolinska Institutet, Stockholm (Sweden)*\r\n\r\nImplementation in Spike2, of protocols used for optogenetic and sensory stimulation of mice.\r\n\r\n**02/2014–07/2014 \tInternship**\r\n\r\n*Karolinska Institutet, Stockholm (Sweden)*\r\n\r\nAnalysis of slow oscillations in electrophysiological recordings of the brain.\r\n\r\n <br />\r\n### EDUCATION AND TRAINING\r\n\r\n----------\r\n**09/2013–10/2014\tErasmus Mundus Master in Systems Biology (euSYSBIO)**\r\n\r\n*Kungliga Tekniska Högskolan, Stockholm (Sweden)*\r\n\r\nFocus on neuroscience and signal processing for biomedical applications.\r\nThesis at Karolinska Institute, in Gilad Silberberg's cortico-striatal microcircuitry lab. Title: \"Catch the dream Wave - Propagation of Cortical Slow Oscillation to the Striatum in anaesthetised mice\".\r\n\r\n**09/2012–05/2013**\r\n\r\n*Aalto School of Science, Helsinki (Finland)*\r\n\r\nFocus on computational biology and machine learning, with a background on life sciences. Developed some wet lab experience on high-throughput technologies.\r\n\r\n**09/2007–07/2012\tIntegrated Master Degree (MSc) in Aerospace Engineering**\r\n\r\n*Instituto Superior Técnico, Universidade de Lisboa (Portugal)*\r\n\r\nCompleted a total of 246 ECTS, with a focus on Avionics (aircraft electronics).\r\nMaster with focus on artificial intelligence, control and systems theory, and microelectronics.\r\nBachelor on mechanics and electronics, in the context of aircrafts.\r\n\r\n**09/2006–07/2007\t1st year of Integrated Master Degree (MSc) in Biological Engineering**\r\n\r\n*Instituto Superior Técnico, Universidade de Lisboa (Portugal)*\r\n\r\nDeveloped knowledge on basic sciences and mathematics for Engineering. Introduction to Life sciences and lab work.\r\n\r\n<br />\r\n###PERSONAL SKILLS\r\n\r\n------------------\r\n\r\n**Mother tongue:** Portuguese\r\n\r\n\r\n**Other languages:** Fluent in English, independent user of French and some knowledge of Spanish.\r\n\r\n**Communication skills:** Good presenter, used to discuss in public and to network on different events (competitions, seminars and workshops).\r\nMulti-cultural communication skills, acquired through my academic studies abroad, cooperation in international projects and participation in European competitions.\r\n\r\n**Computer skills:** Matlab & Simulink - Implemented projects on topics as varied as neuroscience, computational biology, optimal control or computational mathematics.\r\n\r\n\r\nPython - Implemented artificial intelligence algorithms.\r\n\r\n\r\nKnowledge of distributed version control systems such as Git and Github.\r\n\r\n\r\nR - Used for statistical analysis and processing of high-throughput data. \r\n\r\n\r\nBasic knowledge of Java and UML. Used to learn the object oriented programming paradigm.\r\n\r\n\r\nBasic knowledge of C and Fortran, acquired as an undergraduate student.\r\n\r\n\r\nProficient in Microsoft Office suite (Word, Excel, Powerpoint).\r\n\r\n\r\nProficient user of Mac OS X and Windows 7.Some experience with different Linux distributions.\r\n\r\n<br />\r\n\r\n###ADDITIONAL INFORMATION\r\n\r\n-------\r\n\r\n**Other education:** Coursera's Computational Neurosciencecourse, offered by University of Washington.\r\n\r\n\r\nCSC373: Programming a robotic car by Sebastian Thrun, offered by Udacity.\r\n\r\n\r\nIntroduction to Artificial Intelligence by Sebastian Thrun and Peter Norvig, offered by Udacity.\r\n\r\n\r\nWinter Course: 4.5 ECTS, Arctic Science Winter Course 2011, 02/2011 - 03/2011.\r\n\r\n\r\nSummer Course: 10 ECTS, International Engineering Project, 08/2008 - 08/2008.\r\n\r\n\r\nSummer Course: 7.5 ECTS, Human Space Flight and Exploration, 08/2007 -08/2007.\r\n\r\n**Honours and awards:** 6th place in European Aircargo Challenge 2011;\r\n\r\n\r\nParticipant in XXI Portuguese Olympiads of Math;\r\n\r\n**Memberships:** Work developed as member of the Autonomous Section of Applied Aeronautics:\r\n\r\n\r\n* Leader of avionics project in S3A's Lusitânia aircraft;\r\n* Collaborator in S3A's 1st Aeromodelling workshop;\r\n* Coordinator of S3A's 2nd and 3rd Aeromodelling workshop;\r\n+ Member of S3A's Fiscal Councill in 2010.\r\n\t\r\n","google":"","note":"Don't delete this file! It's used internally to help with page regeneration."}